{
"type": "FeatureCollection",
"name": "geo_16_介護療養型医療施設",
"crs": { "type": "name", "properties": { "name": "urn:ogc:def:crs:OGC:1.3:CRS84" } },
"features": [
{ "type": "Feature", "properties": { "緯度": 36.7169437, "経度": 137.2195168000001, "url": "https://www.kaigokensaku.mhlw.go.jp/16/index.php?action_kouhyou_detail_004_kani=true&JigyosyoCd=1610116210-00&ServiceCd=530&Type=search", "url2": "http://www.seikoukai-shimada.jp/", "内容": "清幸会　島田病院【介護療養型医療施設】富山県富山市下新北町6番52号", "サービスの種類": "介護療養型医療施設" }, "geometry": { "type": "Point", "coordinates": [ 137.219516800000065, 36.7169437 ] } },
{ "type": "Feature", "properties": { "緯度": 36.6096965, "経度": 137.2806293, "url": "https://www.kaigokensaku.mhlw.go.jp/16/index.php?action_kouhyou_detail_004_kani=true&JigyosyoCd=1610117176-00&ServiceCd=530&Type=search", "url2": "http://ooyamahp.or.jp/", "内容": "おおやま病院【介護療養型医療施設】富山市花崎８５", "サービスの種類": "介護療養型医療施設" }, "geometry": { "type": "Point", "coordinates": [ 137.280629299999987, 36.6096965 ] } },
{ "type": "Feature", "properties": { "緯度": 36.6313494, "経度": 137.2461623, "url": "https://www.kaigokensaku.mhlw.go.jp/16/index.php?action_kouhyou_detail_004_kani=true&JigyosyoCd=1610116020-00&ServiceCd=530&Type=search", "url2": "http://www.kuriyama-hospital.or.jp", "内容": "栗山病院【介護療養型医療施設】富山市開発133番地", "サービスの種類": "介護療養型医療施設" }, "geometry": { "type": "Point", "coordinates": [ 137.246162300000037, 36.6313494 ] } },
{ "type": "Feature", "properties": { "緯度": 36.7096639, "経度": 137.2163425, "url": "https://www.kaigokensaku.mhlw.go.jp/16/index.php?action_kouhyou_detail_004_kani=true&JigyosyoCd=1610115568-00&ServiceCd=530&Type=search", "url2": "https://masaoka-hp.jp/", "内容": "政岡内科病院【介護療養型医療施設】富山県富山市下新町２８番２３号", "サービスの種類": "介護療養型医療施設" }, "geometry": { "type": "Point", "coordinates": [ 137.2163425, 36.7096639 ] } },
{ "type": "Feature", "properties": { "緯度": 36.63864, "経度": 137.2125873, "url": "https://www.kaigokensaku.mhlw.go.jp/16/index.php?action_kouhyou_detail_004_kani=true&JigyosyoCd=1610114686-00&ServiceCd=530&Type=search", "url2": "http://www.sanikai.or.jp/", "内容": "医療法人社団三医会三輪病院介護療養型医療施設【介護療養型医療施設】富山市小中291", "サービスの種類": "介護療養型医療施設" }, "geometry": { "type": "Point", "coordinates": [ 137.2125873, 36.63864 ] } },
{ "type": "Feature", "properties": { "緯度": 36.6265388, "経度": 137.2439376, "url": "https://www.kaigokensaku.mhlw.go.jp/16/index.php?action_kouhyou_detail_004_kani=true&JigyosyoCd=1610114033-00&ServiceCd=530&Type=search", "url2": null, "内容": "誠友病院【介護療養型医療施設】富山市上千俵町１０３番地", "サービスの種類": "介護療養型医療施設" }, "geometry": { "type": "Point", "coordinates": [ 137.243937599999981, 36.6265388 ] } },
{ "type": "Feature", "properties": { "緯度": 36.6282458, "経度": 137.179438, "url": "https://www.kaigokensaku.mhlw.go.jp/16/index.php?action_kouhyou_detail_004_kani=true&JigyosyoCd=1610118083-00&ServiceCd=530&Type=search", "url2": null, "内容": "萩野病院【介護療養型医療施設】富山市婦中町萩島315-1", "サービスの種類": "介護療養型医療施設" }, "geometry": { "type": "Point", "coordinates": [ 137.179438, 36.6282458 ] } },
{ "type": "Feature", "properties": { "緯度": 36.7072474, "経度": 136.9858168000001, "url": "https://www.kaigokensaku.mhlw.go.jp/16/index.php?action_kouhyou_detail_004_kani=true&JigyosyoCd=1610211995-00&ServiceCd=530&Type=search", "url2": "http://www.shirankai.net/", "内容": "医療法人　光ヶ丘病院【介護療養型医療施設】富山県高岡市西藤平蔵313", "サービスの種類": "介護療養型医療施設" }, "geometry": { "type": "Point", "coordinates": [ 136.985816800000066, 36.7072474 ] } },
{ "type": "Feature", "properties": { "緯度": 36.8103968, "経度": 137.4110766, "url": "https://www.kaigokensaku.mhlw.go.jp/16/index.php?action_kouhyou_detail_004_kani=true&JigyosyoCd=1610410522-00&ServiceCd=530&Type=search", "url2": "http://www.fukujukai.com/", "内容": "医療法人　新川病院【介護療養型医療施設】富山県魚津市住吉２３６番地", "サービスの種類": "介護療養型医療施設" }, "geometry": { "type": "Point", "coordinates": [ 137.4110766, 36.8103968 ] } },
{ "type": "Feature", "properties": { "緯度": 36.8878395, "経度": 137.469502, "url": "https://www.kaigokensaku.mhlw.go.jp/16/index.php?action_kouhyou_detail_004_kani=true&JigyosyoCd=1610710558-00&ServiceCd=530&Type=search", "url2": "http://www4.nsk.ne.jp/ikeda-reha/", "内容": "池田リハビリテーション病院　介護療養型医療施設【介護療養型医療施設】富山県黒部市荻生８２１番地", "サービスの種類": "介護療養型医療施設" }, "geometry": { "type": "Point", "coordinates": [ 137.469502, 36.8878395 ] } }
]
}
