{
"type": "FeatureCollection",
"name": "geo_16_短期入所療養介護（介護医療院）",
"crs": { "type": "name", "properties": { "name": "urn:ogc:def:crs:OGC:1.3:CRS84" } },
"features": [
{ "type": "Feature", "properties": { "緯度": 36.6693754, "経度": 137.212932, "url": "https://www.kaigokensaku.mhlw.go.jp/16/index.php?action_kouhyou_detail_004_kani=true&JigyosyoCd=16B0100022-00&ServiceCd=551&Type=search", "url2": "https://izumikai.mutsumi-gr.jp/", "内容": "いま泉病院　介護医療院【短期入所療養介護（介護医療院）】今泉220番地", "サービスの種類": "短期入所療養介護（介護医療院）" }, "geometry": { "type": "Point", "coordinates": [ 137.212932, 36.6693754 ] } },
{ "type": "Feature", "properties": { "緯度": 36.6313627, "経度": 137.2461752, "url": "https://www.kaigokensaku.mhlw.go.jp/16/index.php?action_kouhyou_detail_004_kani=true&JigyosyoCd=16B0100097-00&ServiceCd=551&Type=search", "url2": "http://kishin-kai.com", "内容": "栗山介護医療院【短期入所療養介護（介護医療院）】富山市開発133番地", "サービスの種類": "短期入所療養介護（介護医療院）" }, "geometry": { "type": "Point", "coordinates": [ 137.24617520000001, 36.6313627 ] } },
{ "type": "Feature", "properties": { "緯度": 36.7072684, "経度": 136.9858488, "url": "https://www.kaigokensaku.mhlw.go.jp/16/index.php?action_kouhyou_detail_004_kani=true&JigyosyoCd=16B0200012-00&ServiceCd=551&Type=search", "url2": "http://shirankai.net/", "内容": "介護医療院　光ヶ丘【短期入所療養介護（介護医療院）】富山県高岡市西藤平蔵313番地", "サービスの種類": "短期入所療養介護（介護医療院）" }, "geometry": { "type": "Point", "coordinates": [ 136.985848800000014, 36.7072684 ] } },
{ "type": "Feature", "properties": { "緯度": 35.0989605, "経度": 138.9027677, "url": "https://www.kaigokensaku.mhlw.go.jp/16/index.php?action_kouhyou_detail_004_kani=true&JigyosyoCd=16B0600013-00&ServiceCd=551&Type=search", "url2": "https://yoshimi-hospital.jp", "内容": "吉見病院　介護医療院　短期入所療養介護【短期入所療養介護（介護医療院）】清水町３番２５号", "サービスの種類": "短期入所療養介護（介護医療院）" }, "geometry": { "type": "Point", "coordinates": [ 138.9027677, 35.0989605 ] } }
]
}
